paignion/__init__.py
paignion/__main__.py
paignion/action_compiler.py
paignion/definitions.py
paignion/exceptions.py
paignion/item.py
paignion/parser.py
paignion/room.py
paignion/tools.py
paignion/used_with_item.py
paignion/frontend/dummy_data.json
paignion/frontend/main.css
paignion/frontend/paignion.js
tests/__init__.py
tests/test_action_compiler.py
tests/test_high_level_cli.py
tests/test_item_object.py
tests/test_room_object.py
tests/test_room_parser.py
tests/test_tools.py
tests/test_used_with_item_object.py
paignion-0.0.6.dist-info/LICENSE
paignion-0.0.6.dist-info/METADATA
paignion-0.0.6.dist-info/WHEEL
paignion-0.0.6.dist-info/entry_points.txt
paignion-0.0.6.dist-info/top_level.txt
paignion-0.0.6.dist-info/RECORD
