Metadata-Version: 2.1
Name: paignion
Version: 0.0.6
Summary: A simple game engine for adventure text games.
Home-page: https://github.com/kokkonisd/paignion
Author: Dimitri Kokkonis
Author-email: kokkonisd@gmail.com
License: UNKNOWN
Platform: UNKNOWN
Classifier: Programming Language :: Python :: 3
Classifier: License :: OSI Approved :: GNU General Public License v3 (GPLv3)
Classifier: Operating System :: OS Independent
Requires-Python: >=3.6
Requires-Dist: pyyaml
Requires-Dist: markdown
Requires-Dist: pymdown-extensions
